eoepca_scim/__init__.py
eoepca_scim/eoepca_scim.py
eoepca_scim/main.py
eoepca_scim-2.8.1.dist-info/LICENSE
eoepca_scim-2.8.1.dist-info/METADATA
eoepca_scim-2.8.1.dist-info/WHEEL
eoepca_scim-2.8.1.dist-info/top_level.txt
eoepca_scim-2.8.1.dist-info/RECORD
