Metadata-Version: 2.1
Name: eoepca-scim
Version: 2.8.1
Summary: Python library to interact with SCIM protocol
Home-page: https://github.com/EOEPCA/um-common-scim-client 
Author: EOEPCA
Author-email: eoepca.systemteam@telespazio.com
License: apache-2.0
Keywords: SCIM,Client,EOEPCA,user,management
Platform: UNKNOWN
Classifier: Development Status :: 3 - Alpha
Classifier: Intended Audience :: Developers
Classifier: Topic :: Software Development :: Build Tools
Requires-Python: >=3.6
License-File: LICENSE
